z3c/recipe/compattest/__init__.py
z3c/recipe/compattest/recipe.py
z3c/recipe/compattest/runner.py
z3c/recipe/compattest/runner.rst
z3c/recipe/compattest/testing.py
z3c/recipe/compattest/tests.py
z3c_recipe_compattest-4.0.dist-info/LICENSE.rst
z3c_recipe_compattest-4.0.dist-info/METADATA
z3c_recipe_compattest-4.0.dist-info/WHEEL
z3c_recipe_compattest-4.0.dist-info/entry_points.txt
z3c_recipe_compattest-4.0.dist-info/top_level.txt
z3c_recipe_compattest-4.0.dist-info/RECORD
