Metadata-Version: 2.2
Name: z3c.recipe.compattest
Version: 4.0
Summary: Buildout recipe to create testrunners for testing compatibility with other packages
Home-page: https://github.com/zopefoundation/z3c.recipe.compattest
Author: Zope Foundation and Contributors
Author-email: zope-dev@zope.dev
License: ZPL-2.1
Project-URL: Issue Tracker, https://github.com/zopefoundation/z3c.recipe.compattest/issues
Project-URL: Sources, https://github.com/zopefoundation/z3c.recipe.compattest
Keywords: zope setuptools egg kgs
Classifier: Framework :: Zope :: 3
Classifier: Intended Audience :: Developers
Classifier: License :: OSI Approved :: Zope Public License
Classifier: Operating System :: OS Independent
Classifier: Programming Language :: Python
Classifier: Programming Language :: Python :: 3
Classifier: Programming Language :: Python :: 3.9
Classifier: Programming Language :: Python :: 3.10
Classifier: Programming Language :: Python :: 3.11
Classifier: Programming Language :: Python :: 3.12
Classifier: Programming Language :: Python :: 3.13
Classifier: Programming Language :: Python :: Implementation :: CPython
Classifier: Programming Language :: Python :: Implementation :: PyPy
Requires-Python: >=3.9
License-File: LICENSE.rst
Requires-Dist: setuptools
Requires-Dist: zc.buildout>=2.0.0
Requires-Dist: zc.recipe.testrunner>=2.0.0
Provides-Extra: test
Requires-Dist: zope.dottedname; extra == "test"
Requires-Dist: zope.testing; extra == "test"
Requires-Dist: manuel; extra == "test"
Dynamic: author
Dynamic: author-email
Dynamic: classifier
Dynamic: description
Dynamic: home-page
Dynamic: keywords
Dynamic: license
Dynamic: project-url
Dynamic: provides-extra
Dynamic: requires-dist
Dynamic: requires-python
Dynamic: summary
